{
  "schemaVersion": 3,
  "meta": {
    "id": "om-oss",
    "title": "Om oss"
  },
  "sections": [
    {
      "id": "sec-om",
      "version": 1,
      "preset": null,
      "size": {
        "minHeight": "672px"
      },
      "grid": {
        "size": 12,
        "snap": true
      },
      "background": {
        "version": 1,
        "layers": [
          {
            "type": "color",
            "version": 1,
            "props": {
              "value": "#0b0e14"
            }
          }
        ]
      },
      "blocks": [
        {
          "id": "blk-om-tittel",
          "type": "text",
          "version": 1,
          "props": {
            "html": "<h1>Om oss</h1>",
            "align": "left"
          },
          "animation": null,
          "frames": {
            "desktop": {
              "x": 8.33,
              "y": 24,
              "w": 50,
              "h": 24,
              "z": 1,
              "rot": 0
            },
            "mobile": null
          }
        },
        {
          "id": "blk-om-tekst",
          "type": "text",
          "version": 1,
          "props": {
            "html": "<p>Skriv om foreningen din her. Denne seksjonen er bygget fra tomt lerret og bruker et eget grid (12 kolonner).</p>",
            "align": "left"
          },
          "animation": null,
          "frames": {
            "desktop": {
              "x": 16.67,
              "y": 144,
              "w": 58.33,
              "h": 36,
              "z": 1,
              "rot": 0
            },
            "mobile": null
          }
        },
        {
          "id": "blk-81932d51",
          "type": "shape",
          "version": 1,
          "props": {
            "kind": "line",
            "color": "accent",
            "thickness": 2,
            "fill": null
          },
          "animation": null,
          "frames": {
            "desktop": {
              "x": 8.33,
              "y": 300,
              "w": 50,
              "h": 12,
              "z": 1,
              "rot": 0
            },
            "mobile": null
          }
        },
        {
          "id": "blk-f88814b6",
          "type": "text",
          "version": 1,
          "props": {
            "html": "<p>Dette er supert!!</p>",
            "align": "left"
          },
          "animation": null,
          "frames": {
            "desktop": {
              "x": 49.7,
              "y": 228,
              "w": 33,
              "h": 28,
              "z": 1,
              "rot": 0
            },
            "mobile": null
          }
        },
        {
          "id": "blk-3a9f0c14",
          "type": "shape",
          "version": 1,
          "props": {
            "kind": "line",
            "color": "accent",
            "thickness": 2,
            "fill": null
          },
          "animation": null,
          "frames": {
            "desktop": {
              "x": 46.55,
              "y": 240,
              "w": 11.05,
              "h": 4,
              "z": 1,
              "rot": 0
            },
            "mobile": null
          }
        }
      ],
      "responsive": {
        "mobile": {
          "mode": "auto",
          "attention": null
        }
      }
    }
  ]
}
